sphinxcontrib_globalsubs-0.1.2-py3.12-nspkg.pth
sphinxcontrib/globalsubs.py
sphinxcontrib_globalsubs-0.1.2.dist-info/LICENSE.txt
sphinxcontrib_globalsubs-0.1.2.dist-info/METADATA
sphinxcontrib_globalsubs-0.1.2.dist-info/WHEEL
sphinxcontrib_globalsubs-0.1.2.dist-info/namespace_packages.txt
sphinxcontrib_globalsubs-0.1.2.dist-info/top_level.txt
sphinxcontrib_globalsubs-0.1.2.dist-info/RECORD
