Metadata-Version: 2.1
Name: sphinxcontrib-globalsubs
Version: 0.1.2
Summary: Sphinx global substitutions extension
Home-page: https://github.com/missinglinkelectronics/sphinxcontrib-globalsubs
Download-URL: https://pypi.org/project/sphinxcontrib-globalsubs
Author: Stefan Wiehler
Author-email: sphinx_contribute@missinglinkelectronics.com
License: BSD
Platform: any
Classifier: Development Status :: 4 - Beta
Classifier: Environment :: Console
Classifier: Environment :: Web Environment
Classifier: Intended Audience :: Developers
Classifier: License :: OSI Approved :: BSD License
Classifier: Operating System :: OS Independent
Classifier: Programming Language :: Python :: 3
Classifier: Framework :: Sphinx :: Extension
Classifier: Topic :: Documentation
Classifier: Topic :: Utilities
Requires-Python: ~=3.4
License-File: LICENSE.txt
Requires-Dist: Sphinx>=1.6
